fbchat_wrapper/__init__.py
fbchat_wrapper/fbchat_wrapper.py
fbchat_wrapper/utils.py
fbchat_wrapper-0.2.6.dist-info/METADATA
fbchat_wrapper-0.2.6.dist-info/WHEEL
fbchat_wrapper-0.2.6.dist-info/top_level.txt
fbchat_wrapper-0.2.6.dist-info/RECORD
